README.md
setup.py
ns_record/__init__.py
ns_record.egg-info/PKG-INFO
ns_record.egg-info/SOURCES.txt
ns_record.egg-info/dependency_links.txt
ns_record.egg-info/entry_points.txt
ns_record.egg-info/requires.txt
ns_record.egg-info/top_level.txt