Metadata-Version: 1.1
Name: ns-record
Version: 1.0.8
Summary: 修改云厂商域名解析记录
Home-page: https://newops.cn/15077893526985.html
Author: wangsir
Author-email: wanglin@dbca.cn
License: GPLv2
Platform: UNKNOWN
Classifier: Programming Language :: Python
Classifier: Programming Language :: Python :: 2.7
